<?xml version="1.0" encoding="utf-8"?>
<SoundBanksInfo Platform="Windows" BasePlatform="Windows" SchemaVersion="16" SoundBankVersion="150">
	<RootPaths>
		<ProjectRoot>../..</ProjectRoot>
		<SourceFilesRoot>../../.cache/Windows</SourceFilesRoot>
		<SoundBanksRoot>.</SoundBanksRoot>
		<ExternalSourcesInputFile></ExternalSourcesInputFile>
		<ExternalSourcesOutputRoot>.</ExternalSourcesOutputRoot>
	</RootPaths>
	<DialogueEvents/>
	<SoundBanks>
		<SoundBank Id="133642231" Type="User" Language="SFX" Hash="{1BEC1E16-EA43-8005-8CB3-6FF8B0F45C0E}">
			<ShortName>General</ShortName>
			<Path>General.bnk</Path>
			<Media>
				<File Id="245429244" Language="SFX" Streaming="false" Location="Memory">
					<ShortName>GameMusic.wav</ShortName>
					<CachePath>SFX/GameMusic_56CEF360.wem</CachePath>
				</File>
				<File Id="271268207" Language="SFX" Streaming="false" Location="Memory">
					<ShortName>Temp_MIDI.mid</ShortName>
					<CachePath>SFX/Temp_MIDI_36E4615E.wem</CachePath>
				</File>
			</Media>
			<Plugins>
				<Custom>
					<Plugin Id="599441268" Name="Silence" LibName="Wwise Silence" LibId="6619138"/>
				</Custom>
			</Plugins>
			<Events>
				<Event Id="3092587493" Name="Pause" MaxAttenuation="0" DurationType="OneShot" DurationMin="0" DurationMax="0"/>
				<Event Id="953277036" Name="Resume" MaxAttenuation="0" DurationType="OneShot" DurationMin="0" DurationMax="0"/>
				<Event Id="1568977742" Name="StartGameMusic" DurationType="OneShot" DurationMin="111.844666" DurationMax="111.844666">
					<MediaRefs>
						<MediaRef Id="245429244"/>
						<MediaRef Id="271268207"/>
					</MediaRefs>
					<PluginRefs>
						<Custom>
							<PluginRef Id="599441268"/>
						</Custom>
					</PluginRefs>
				</Event>
			</Events>
		</SoundBank>
		<SoundBank Id="1355168291" Type="User" Language="SFX" Hash="{D99FD475-90DE-DB2B-8078-97B90265E393}">
			<ShortName>Init</ShortName>
			<Path>Init.bnk</Path>
			<Plugins>
				<AudioDevices>
					<Plugin Id="2317455096" Name="No_Output" LibName="No Output" LibId="11862023"/>
					<Plugin Id="3859886410" Name="System" LibName="System" LibId="11403271"/>
				</AudioDevices>
			</Plugins>
			<Busses>
				<Bus Id="3803692087" Name="Master Audio Bus"/>
			</Busses>
		</SoundBank>
	</SoundBanks>
	<FileHash>{476B6DB4-EB69-1ED9-A920-6954CC5D5DBD}</FileHash>
</SoundBanksInfo>
